setup.cfg
setup.py
type_safety.egg-info/PKG-INFO
type_safety.egg-info/SOURCES.txt
type_safety.egg-info/dependency_links.txt
type_safety.egg-info/requires.txt
type_safety.egg-info/top_level.txt
typesafety/__init__.py
typesafety/typesafety.py