Metadata-Version: 1.1
Name: type-safety
Version: 0.4
Summary: python decorators to enable type-safety on python functions, classes, and generators.
Home-page: https://github.com/WillBrennan/type-safety
Author: WillBrennan
Author-email: WillBrennan@users.noreply.github.com
License: MIT
Download-URL: https://github.com/WillBrennan/type-safety/tarball/0.4
Keywords: type-safety,type-safe,type,safe,safety,functions,classes,generators
Platform: UNKNOWN
